odoo/addons/pms_account/README.rst
odoo/addons/pms_account/__init__.py
odoo/addons/pms_account/__manifest__.py
odoo/addons/pms_account/i18n/es.po
odoo/addons/pms_account/i18n/pms_account.pot
odoo/addons/pms_account/models/__init__.py
odoo/addons/pms_account/models/account_move.py
odoo/addons/pms_account/models/account_move_line.py
odoo/addons/pms_account/models/pms_property.py
odoo/addons/pms_account/models/pms_service.py
odoo/addons/pms_account/readme/CONFIGURE.rst
odoo/addons/pms_account/readme/CONTRIBUTORS.rst
odoo/addons/pms_account/readme/DESCRIPTION.rst
odoo/addons/pms_account/readme/USAGE.rst
odoo/addons/pms_account/static/description/agency_logo.png
odoo/addons/pms_account/static/description/agency_logo1.png
odoo/addons/pms_account/static/description/avatar.png
odoo/addons/pms_account/static/description/icon.png
odoo/addons/pms_account/static/description/index.html
odoo/addons/pms_account/views/account_move.xml
odoo/addons/pms_account/views/pms_property.xml
odoo14_addon_pms_account-14.0.1.0.1.dev2.dist-info/METADATA
odoo14_addon_pms_account-14.0.1.0.1.dev2.dist-info/WHEEL
odoo14_addon_pms_account-14.0.1.0.1.dev2.dist-info/top_level.txt
odoo14_addon_pms_account-14.0.1.0.1.dev2.dist-info/RECORD
